README.md
setup.cfg
setup.py
more_transformers/__init__.py
more_transformers/common.py
more_transformers/decomposition.py
more_transformers/preprocessing.py
more_transformers.egg-info/PKG-INFO
more_transformers.egg-info/SOURCES.txt
more_transformers.egg-info/dependency_links.txt
more_transformers.egg-info/requires.txt
more_transformers.egg-info/top_level.txt