Metadata-Version: 2.1
Name: more-transformers
Version: 0.0.11
Summary: More transformers for scikit-learn pipelines
Home-page: https://github.com/mkleinbort/more-transformers
Author: Mycchaka Kleinbort
Author-email: mkleinbort@gmail.com
License: UNKNOWN
Project-URL: Bug Reports, https://github.com/mkleinbort/more-transformers/issues
Project-URL: Source, https://github.com/mkleinbort/more-transformers/
Keywords: sklearn pipeline ml ai pandas
Platform: any
Classifier: Development Status :: 3 - Alpha
Classifier: Intended Audience :: Developers
Classifier: Topic :: Scientific/Engineering :: Artificial Intelligence
Classifier: License :: OSI Approved :: MIT License
Classifier: Programming Language :: Python :: 3.6
Classifier: Programming Language :: Python :: 3.7
Classifier: Programming Language :: Python :: 3.8
Requires-Python: >=3.6
